{
  "data": [
    {
      "id": "1",
      "area": "NCR",
      "surname": "Dela Cruz",
      "firstname": "Juan",
      "middlename": "tamad",
      "relationshipToAfpMember": "apaps",
      "currentAddress": "Somewhere",
      "provincialAddress": "Somewhere",
      "phoneNumber": "2121121",
      "cellphoneNumber": "0909090909",
      "emailAddress": "juantamad@gmail.com",
      "birthDate": "09/09/1999",
      "birthPlace": "somewhere in manila",
      "sex": "Male",
      "civilStatus": "Single",
      "religion": "Roman Catholic",
      "schoolIntendedToEnrollIn": "TUP",
      "schoolAddress": "somewhere",
      "educationLevel": "not stated",
      "yearLevel": "not stated",
      "course": "not stated",
      
      "afp_surname": "not stated",
      "afp_firstname": "not stated",
      "afp_middleInitial": "not stated",
      "afp_rank": "not stated",
      "afp_SN": "not stated",
      "afp_branchOfService": "not stated",
      "afp_militaryStatus": "not stated",
      "afp_unitAssignment": "not stated",
      "afp_currentAddress": "not stated",
      "afp_phoneNo": "string",
      "afp_cellPhoneNo": "string",
      "afp_emailAddress": "string",
      "afp_birthDate": "string",
      "afp_birthPlace": "string",
      "afp_sex": "string",
      "afp_civilStatus": "string",
      "afp_nrOfDependents": "string",
      "afp_nameOfLegalDependents": "string",
      "afp_dependentsBirthdate": "string",
      "afp_dependentsYearLevel": "string",
      "afp_educationalProgramAvailed": "string",

      "guardian_surname": "string",
      "guardian_firstName": "string",
      "guardian_MiddleName": "string",
      "guardian_relationshipToApplicant": "string",
      "guardian_currentAddress": "string",
      "guardian_provincialAddress": "string",
      "guardian_emailAddress": "string",
      "guardian_cellPhoneNo": "string",
      "guardian_phoneNo": "string",

      "signatureOfApplicant": "string",
      "signatureOfAfporGuardian": "string",

      "nameOfAfpPersonnel": "string",
      "dateReceived": "string"
    },
    {
      "id": "2",
      "area": "NCR",
      "surname": "Notarte",
      "firstname": "Allain John",
      "middlename": "Tayag",
      "relationshipToAfpMember": "apaps",
      "currentAddress": "Somewhere",
      "provincialAddress": "Somewhere",
      "phoneNumber": "2121121",
      "cellphoneNumber": "0909090909",
      "emailAddress": "juantamad@gmail.com",
      "birthDate": "09/09/1999",
      "birthPlace": "somewhere in manila",
      "sex": "Male",
      "civilStatus": "Single",
      "religion": "Roman Catholic",
      "schoolIntendedToEnrollIn": "TUP",
      "schoolAddress": "somewhere",
      "educationLevel": "not stated",
      "yearLevel": "not stated",
      "course": "not stated",
      
      "afp_surname": "not stated",
      "afp_firstname": "not stated",
      "afp_middleInitial": "not stated",
      "afp_rank": "not stated",
      "afp_SN": "not stated",
      "afp_branchOfService": "not stated",
      "afp_militaryStatus": "not stated",
      "afp_unitAssignment": "not stated",
      "afp_currentAddress": "not stated",
      "afp_phoneNo": "string",
      "afp_cellPhoneNo": "string",
      "afp_emailAddress": "string",
      "afp_birthDate": "string",
      "afp_birthPlace": "string",
      "afp_sex": "string",
      "afp_civilStatus": "string",
      "afp_nrOfDependents": "string",
      "afp_nameOfLegalDependents": "string",
      "afp_dependentsBirthdate": "string",
      "afp_dependentsYearLevel": "string",
      "afp_educationalProgramAvailed": "string",

      "guardian_surname": "string",
      "guardian_firstName": "string",
      "guardian_MiddleName": "string",
      "guardian_relationshipToApplicant": "string",
      "guardian_currentAddress": "string",
      "guardian_provincialAddress": "string",
      "guardian_emailAddress": "string",
      "guardian_cellPhoneNo": "string",
      "guardian_phoneNo": "string",

      "signatureOfApplicant": "string",
      "signatureOfAfporGuardian": "string",

      "nameOfAfpPersonnel": "string",
      "dateReceived": "string"
    },
    {
      "id": "3",
      "area": "NCR",
      "surname": "Villar",
      "firstname": "Eugine",
      "middlename": "",
      "relationshipToAfpMember": "apaps",
      "currentAddress": "Somewhere",
      "provincialAddress": "Somewhere",
      "phoneNumber": "2121121",
      "cellphoneNumber": "0909090909",
      "emailAddress": "juantamad@gmail.com",
      "birthDate": "09/09/1999",
      "birthPlace": "somewhere in manila",
      "sex": "Male",
      "civilStatus": "Single",
      "religion": "Roman Catholic",
      "schoolIntendedToEnrollIn": "TUP",
      "schoolAddress": "somewhere",
      "educationLevel": "not stated",
      "yearLevel": "not stated",
      "course": "not stated",
      
      "afp_surname": "not stated",
      "afp_firstname": "not stated",
      "afp_middleInitial": "not stated",
      "afp_rank": "not stated",
      "afp_SN": "not stated",
      "afp_branchOfService": "not stated",
      "afp_militaryStatus": "not stated",
      "afp_unitAssignment": "not stated",
      "afp_currentAddress": "not stated",
      "afp_phoneNo": "string",
      "afp_cellPhoneNo": "string",
      "afp_emailAddress": "string",
      "afp_birthDate": "string",
      "afp_birthPlace": "string",
      "afp_sex": "string",
      "afp_civilStatus": "string",
      "afp_nrOfDependents": "string",
      "afp_nameOfLegalDependents": "string",
      "afp_dependentsBirthdate": "string",
      "afp_dependentsYearLevel": "string",
      "afp_educationalProgramAvailed": "string",

      "guardian_surname": "string",
      "guardian_firstName": "string",
      "guardian_MiddleName": "string",
      "guardian_relationshipToApplicant": "string",
      "guardian_currentAddress": "string",
      "guardian_provincialAddress": "string",
      "guardian_emailAddress": "string",
      "guardian_cellPhoneNo": "string",
      "guardian_phoneNo": "string",

      "signatureOfApplicant": "string",
      "signatureOfAfporGuardian": "string",

      "nameOfAfpPersonnel": "string",
      "dateReceived": "string"
    }
  ]
}